fsdetection/__init__.py
fsdetection/datasets/__init__.py
fsdetection/datasets/fs_arrow_dataset.py
fsdetection/datasets/fs_builder.py
fsdetection/datasets/fs_load.py
fsdetection/datasets/packaged_modules.lock
fsdetection/datasets/packaged_modules/__init__.py
fsdetection/datasets/packaged_modules/parquet/__init__.py
fsdetection/datasets/packaged_modules/parquet/fs_parquet.py
fsdetection/transformers/__init__.py
fsdetection/transformers/fs_trainer.py
fsdetection-0.0.5.dist-info/METADATA
fsdetection-0.0.5.dist-info/WHEEL
fsdetection-0.0.5.dist-info/licenses/LICENSE
fsdetection-0.0.5.dist-info/RECORD
