Metadata-Version: 2.4
Name: fsdetection
Version: 0.0.5
Summary: package to simplify few-shot object detection
Project-URL: Homepage, https://github.com/HichTala/fsdetection
Project-URL: Issues, https://github.com/HichTala/fsdetection/issues
Author-email: HichTala <hich.tala.phd@gmail.com>
License-File: LICENSE
Classifier: License :: OSI Approved :: MIT License
Classifier: Operating System :: OS Independent
Classifier: Programming Language :: Python :: 3
Requires-Python: >=3.8
